common_harness_lib/__init__.py
common_harness_lib/common_harness_lib.py
common_harness_lib/test.py
common_harness_lib-0.0.18.dist-info/METADATA
common_harness_lib-0.0.18.dist-info/WHEEL
common_harness_lib-0.0.18.dist-info/top_level.txt
common_harness_lib-0.0.18.dist-info/RECORD
