Metadata-Version: 2.1
Name: common-harness-lib
Version: 0.0.18
Summary: Helper package for H2H Task images.
Home-page: https://github.com/2hal/common-harness-lib
Author: Highway to HAL
Author-email: h2h@georgeom.net
License: UNKNOWN
Platform: UNKNOWN
Classifier: Programming Language :: Python :: 3
Classifier: License :: OSI Approved :: MIT License
Classifier: Operating System :: OS Independent
Requires-Python: >=3.6
Requires-Dist: boto3
Requires-Dist: botocore
